{
  "title": "Test Experiment",
  "types": ["Experiment"],
  "creators": ["Tristan Kuehn"],
  "licenses": [{"name": "license"}],
  "description": "A test experiment for CONP Experiments",
  "keywords": ["a", {"value": "word"}],
  "version": "0.1.0",
  "distributions": [],
  "extraProperties": [
    {
      "category": "experimentProperties",
      "value": {
        "functionAssessed": "None",
        "languages": ["English"],
        "validation": [],
        "accessibility": [],
        "requirements": {
          "platforms": ["Computer"],
          "devices": ["Device1"],
          "software": ["Program1"]
        }
      }
    ]
  }
}
